{
    "ScenarioPlugin.sfc_add_flowclassifier": [
        {
            "args": {
                "src_cidr": "192.168.100.0/24",
                "dest_cidr": "192.168.200.0/24",
                "image": "d8b5060a-ef63-4b01-8b79-083ae8866aaf",
                "flavor": "tiny",
                "public_net": "219269de-40ca-4dfa-875b-5c332add62df",
                "username" : "root",
                "password" : "noir0123"
            },
            "runner": {
                "type": "serial",
                "times": 1
            }
        }
    ]
}

